{
  "users": [
    {
      "id": "jferrergil1@gmail.com",
      "fav": [
        {
          "id": "",
          "name": "",
          "thumb": "",
          "apiId": ""
        },
        {},
        {
          "name": "Bobby Burns Cocktail",
          "thumb": "https://www.thecocktaildb.com/images/media/drink/km6se51484411608.jpg",
          "apiId": "11121",
          "id": "e1edb96e-599b-4e0d-aab6-9e73ac8290b4"
        }
      ],
      "custom": [
        {
          "name": "",
          "thumb": "",
          "recipe": "",
          "type": "",
          "glass": "",
          "alcoholic": "",
          "ingredientes": [
            ""
          ],
          "ingredientesAmount": [
            ""
          ],
          "id": ""
        }
      ]
    },
    {
      "id": "berserksnake976@gmail.com",
      "fav": [
        {
          "id": "",
          "name": "",
          "thumb": "",
          "apiId": ""
        },
        {
          "name": "9 1/2 Weeks",
          "thumb": "https://www.thecocktaildb.com/images/media/drink/xvwusr1472669302.jpg",
          "apiId": "16108",
          "id": "235685a0-608e-43eb-801c-46ed22ebbf88"
        },
        {
          "name": "24k nightmare",
          "thumb": "https://www.thecocktaildb.com/images/media/drink/yyrwty1468877498.jpg",
          "apiId": "17060",
          "id": "e64ab96a-5ea1-42da-8a14-32e3b506a106"
        }
      ],
      "custom": [
        {
          "name": "",
          "thumb": "",
          "recipe": "",
          "type": "",
          "glass": "",
          "alcoholic": "",
          "ingredientes": [
            ""
          ],
          "ingredientesAmount": [
            ""
          ],
          "id": ""
        }
      ]
    },
    {
      "id": "johndoe@me.com",
      "fav": [
        {
          "id": "",
          "name": "",
          "thumb": "",
          "apiId": ""
        },
        {
          "id": "asdasdasd",
          "name": "Mock Cocktail",
          "thumb": "https://www.thecocktaildb.com/images/media/drink/xvwusr1472669302.jpg",
          "apiId": "12345"
        }
      ],
      "custom": [
        {
          "name": "",
          "thumb": "",
          "recipe": "",
          "type": "",
          "glass": "",
          "alcoholic": "",
          "ingredientes": [
            ""
          ],
          "ingredientesAmount": [
            ""
          ],
          "id": ""
        },
        {
          "status": "",
          "id": "442859cc-e0b6-41ae-8108-2ff417385a69",
          "name": "El mio custom",
          "recipe": "Custom recipe",
          "type": "Ordinary Drink",
          "glass": "Cocktail glass",
          "alcoholic": "Alcoholic",
          "ingredients": [
            "",
            "Vodka",
            "Gin"
          ],
          "amount": [
            "",
            "",
            ""
          ],
          "ingredientes": [
            "",
            "Vodka",
            "Gin"
          ],
          "ingredientesAmount": [
            "",
            "",
            ""
          ]
        },
        {
          "status": "",
          "id": "6b88106f-69c9-48e9-91a7-40bb76a6eda1",
          "name": "El mio custom",
          "recipe": "Custom recipe",
          "type": "Ordinary Drink",
          "glass": "Cocktail glass",
          "alcoholic": "Alcoholic",
          "ingredients": [
            "",
            "Vodka",
            "Gin"
          ],
          "amount": [
            "",
            "",
            ""
          ],
          "ingredientes": [
            "",
            "Vodka",
            "Gin"
          ],
          "ingredientesAmount": [
            "",
            "",
            ""
          ]
        },
        {
          "status": "",
          "id": "b4ca86e7-4bf6-4a3d-8398-01f55feb92ba",
          "name": "El mio custom",
          "recipe": "Custom recipe",
          "type": "Ordinary Drink",
          "glass": "Cocktail glass",
          "alcoholic": "Alcoholic",
          "ingredients": [
            "",
            "Vodka",
            "Gin"
          ],
          "amount": [
            "",
            "",
            ""
          ],
          "ingredientes": [
            "",
            "Vodka",
            "Gin"
          ],
          "ingredientesAmount": [
            "",
            "",
            ""
          ]
        },
        {
          "status": "",
          "id": "a767034c-8e03-428e-bb1a-a6a49398c581",
          "name": "El mio custom",
          "recipe": "Custom recipe",
          "type": "Ordinary Drink",
          "glass": "Cocktail glass",
          "alcoholic": "Alcoholic",
          "ingredients": [
            "",
            "Vodka",
            "Gin"
          ],
          "amount": [
            "",
            "",
            ""
          ],
          "ingredientes": [
            "",
            "Vodka",
            "Gin"
          ],
          "ingredientesAmount": [
            "",
            "",
            ""
          ]
        },
        {
          "status": "",
          "id": "47399e7e-677f-4b4f-9b48-62236342ece2",
          "name": "El mio custom",
          "recipe": "Custom recipe",
          "type": "Ordinary Drink",
          "glass": "Cocktail glass",
          "alcoholic": "Alcoholic",
          "ingredients": [
            "",
            "Vodka",
            "Gin"
          ],
          "amount": [
            "",
            "",
            ""
          ],
          "ingredientes": [
            "",
            "Vodka",
            "Gin"
          ],
          "ingredientesAmount": [
            "",
            "",
            ""
          ]
        },
        {
          "status": "",
          "id": "1302501d-c935-4bc3-9909-f941ced0c77b",
          "name": "El mio custom",
          "recipe": "Custom recipe",
          "type": "Ordinary Drink",
          "glass": "Cocktail glass",
          "alcoholic": "Alcoholic",
          "ingredients": [
            "",
            "Vodka",
            "Gin"
          ],
          "amount": [
            "",
            "",
            ""
          ],
          "ingredientes": [
            "",
            "Vodka",
            "Gin"
          ],
          "ingredientesAmount": [
            "",
            "",
            ""
          ]
        },
        {
          "status": "",
          "id": "7262051f-041b-4f5e-a9a4-ce25a2a7a0b0",
          "name": "El mio custom",
          "recipe": "Custom recipe",
          "type": "Ordinary Drink",
          "glass": "Cocktail glass",
          "alcoholic": "Alcoholic",
          "ingredients": [
            "",
            "Vodka",
            "Gin"
          ],
          "amount": [
            "",
            "",
            ""
          ],
          "ingredientes": [
            "",
            "Vodka",
            "Gin"
          ],
          "ingredientesAmount": [
            "",
            "",
            ""
          ]
        },
        {
          "status": "",
          "id": "90dae5ca-b882-4cc2-b088-9106de15c8b3",
          "name": "El mio custom",
          "recipe": "Custom recipe",
          "type": "Ordinary Drink",
          "glass": "Cocktail glass",
          "alcoholic": "Alcoholic",
          "ingredients": [
            "",
            "Vodka",
            "Gin"
          ],
          "amount": [
            "",
            "",
            ""
          ],
          "ingredientes": [
            "",
            "Vodka",
            "Gin"
          ],
          "ingredientesAmount": [
            "",
            "",
            ""
          ]
        },
        {
          "status": "",
          "id": "2b0ae760-10ad-4603-8baa-358cb93c5a33",
          "name": "El mio custom",
          "recipe": "Custom recipe",
          "type": "Ordinary Drink",
          "glass": "Cocktail glass",
          "alcoholic": "Alcoholic",
          "ingredients": [
            "",
            "Vodka",
            "Gin"
          ],
          "amount": [
            "",
            "",
            ""
          ],
          "ingredientes": [
            "",
            "Vodka",
            "Gin"
          ],
          "ingredientesAmount": [
            "",
            "",
            ""
          ]
        },
        {
          "status": "",
          "id": "47069eda-d793-47c4-abec-54aae5eb8fd8",
          "name": "El mio custom",
          "recipe": "Custom recipe",
          "type": "Ordinary Drink",
          "glass": "Cocktail glass",
          "alcoholic": "Alcoholic",
          "ingredients": [
            "",
            "Vodka",
            "Gin"
          ],
          "amount": [
            "",
            "",
            ""
          ],
          "ingredientes": [
            "",
            "Vodka",
            "Gin"
          ],
          "ingredientesAmount": [
            "",
            "",
            ""
          ]
        },
        {
          "status": "",
          "id": "ebb24c0e-5ad1-42f7-9c1c-121b600a5fc9",
          "name": "El mio custom",
          "recipe": "Custom recipe",
          "type": "Ordinary Drink",
          "glass": "Cocktail glass",
          "alcoholic": "Alcoholic",
          "ingredients": [
            "",
            "Vodka",
            "Gin"
          ],
          "amount": [
            "",
            "",
            ""
          ],
          "ingredientes": [
            "",
            "Vodka",
            "Gin"
          ],
          "ingredientesAmount": [
            "",
            "",
            ""
          ]
        },
        {
          "status": "",
          "id": "21e0126c-d4ca-4b2e-a5fc-eb01f210f32f",
          "name": "El mio custom",
          "recipe": "Custom recipe",
          "type": "Ordinary Drink",
          "glass": "Cocktail glass",
          "alcoholic": "Alcoholic",
          "ingredients": [
            "",
            "Vodka",
            "Gin"
          ],
          "amount": [
            "",
            "",
            ""
          ],
          "ingredientes": [
            "",
            "Vodka",
            "Gin"
          ],
          "ingredientesAmount": [
            "",
            "",
            ""
          ]
        },
        {
          "status": "",
          "id": "e7800884-1f5a-48f1-a461-23e5595674fc",
          "name": "El mio custom",
          "recipe": "Custom recipe",
          "type": "Ordinary Drink",
          "glass": "Cocktail glass",
          "alcoholic": "Alcoholic",
          "ingredients": [
            "",
            "Vodka",
            "Gin"
          ],
          "amount": [
            "",
            "",
            ""
          ],
          "ingredientes": [
            "",
            "Vodka",
            "Gin"
          ],
          "ingredientesAmount": [
            "",
            "",
            ""
          ]
        },
        {
          "status": "",
          "id": "e14c5b1e-3f6b-410b-8cf2-e673918914ca",
          "name": "El mio custom",
          "recipe": "Custom recipe",
          "type": "Ordinary Drink",
          "glass": "Cocktail glass",
          "alcoholic": "Alcoholic",
          "ingredients": [
            "",
            "Vodka",
            "Gin"
          ],
          "amount": [
            "",
            "",
            ""
          ],
          "ingredientes": [
            "",
            "Vodka",
            "Gin"
          ],
          "ingredientesAmount": [
            "",
            "",
            ""
          ]
        },
        {
          "status": "",
          "id": "8ef90bc2-4f34-486b-a914-72f5eaf33da0",
          "name": "El mio custom",
          "recipe": "Custom recipe",
          "type": "Ordinary Drink",
          "glass": "Cocktail glass",
          "alcoholic": "Alcoholic",
          "ingredients": [
            "",
            "Vodka",
            "Gin"
          ],
          "amount": [
            "",
            "",
            ""
          ],
          "ingredientes": [
            "",
            "Vodka",
            "Gin"
          ],
          "ingredientesAmount": [
            "",
            "",
            ""
          ]
        },
        {
          "status": "",
          "id": "78a7b25a-dda2-4351-8e98-6f53ca07553c",
          "name": "El mio custom",
          "recipe": "Custom recipe",
          "type": "Ordinary Drink",
          "glass": "Cocktail glass",
          "alcoholic": "Alcoholic",
          "ingredients": [
            "",
            "Vodka",
            "Gin"
          ],
          "amount": [
            "",
            "",
            ""
          ],
          "ingredientes": [
            "",
            "Vodka",
            "Gin"
          ],
          "ingredientesAmount": [
            "",
            "",
            ""
          ]
        },
        {
          "name": "My custom",
          "recipe": "Custom recipe",
          "type": "Ordinary Drink",
          "glass": "Cocktail glass",
          "alcoholic": "Alcoholic",
          "ingredientes": [
            "",
            "Vodka",
            "Gin"
          ],
          "ingredientesAmount": [
            "",
            "",
            ""
          ],
          "id": "e76fbe12-bda3-4c81-a41d-9337827b27bd"
        },
        {
          "name": "My custom",
          "recipe": "Custom recipe",
          "type": "Ordinary Drink",
          "glass": "Cocktail glass",
          "alcoholic": "Alcoholic",
          "ingredientes": [
            "",
            "Vodka",
            "Gin"
          ],
          "ingredientesAmount": [
            "",
            "",
            ""
          ],
          "id": "07412883-f35f-439b-b220-a72882d79253"
        },
        {
          "name": "My custom",
          "recipe": "Custom recipe",
          "type": "Ordinary Drink",
          "glass": "Cocktail glass",
          "alcoholic": "Alcoholic",
          "ingredientes": [
            "",
            "Vodka",
            "Gin"
          ],
          "ingredientesAmount": [
            "",
            "",
            ""
          ],
          "id": "fc1baf17-a115-4e69-b211-53bc17c37d3e"
        },
        {
          "name": "My custom",
          "recipe": "Custom recipe",
          "type": "Ordinary Drink",
          "glass": "Cocktail glass",
          "alcoholic": "Alcoholic",
          "ingredientes": [
            "",
            "Vodka",
            "Gin"
          ],
          "ingredientesAmount": [
            "",
            "",
            ""
          ],
          "id": "92d3dc2c-69f0-4882-b700-9ded0ccbc3ea"
        },
        {
          "name": "My custom",
          "recipe": "Custom recipe",
          "type": "Ordinary Drink",
          "glass": "Cocktail glass",
          "alcoholic": "Alcoholic",
          "ingredientes": [
            "",
            "Vodka",
            "Gin"
          ],
          "ingredientesAmount": [
            "",
            "",
            ""
          ],
          "id": "5579a163-ca0c-46b1-a04a-1275b225a869"
        },
        {
          "name": "My custom",
          "recipe": "Custom recipe",
          "type": "Ordinary Drink",
          "glass": "Cocktail glass",
          "alcoholic": "Alcoholic",
          "ingredientes": [
            "",
            "Vodka",
            "Gin"
          ],
          "ingredientesAmount": [
            "",
            "",
            ""
          ],
          "id": "8cf75f5b-cec3-4839-9300-caba58b190e7"
        },
        {
          "name": "My custom",
          "recipe": "Custom recipe",
          "type": "Ordinary Drink",
          "glass": "Cocktail glass",
          "alcoholic": "Alcoholic",
          "ingredientes": [
            "",
            "Vodka",
            "Gin"
          ],
          "ingredientesAmount": [
            "",
            "",
            ""
          ],
          "id": "fee721c0-fa71-4aef-8a34-eb5e07d1eb99"
        },
        {
          "name": "My custom",
          "recipe": "Custom recipe",
          "type": "Ordinary Drink",
          "glass": "Cocktail glass",
          "alcoholic": "Alcoholic",
          "ingredientes": [
            "",
            "Vodka",
            "Gin"
          ],
          "ingredientesAmount": [
            "",
            "",
            ""
          ],
          "id": "96d88743-4bc5-4962-9c18-9c928df4b927"
        },
        {
          "name": "My custom",
          "recipe": "Custom recipe",
          "type": "Ordinary Drink",
          "glass": "Cocktail glass",
          "alcoholic": "Alcoholic",
          "ingredientes": [
            "",
            "Vodka",
            "Gin"
          ],
          "ingredientesAmount": [
            "",
            "",
            ""
          ],
          "id": "6b44f54b-3e63-4c12-977b-878d8cbe8085"
        },
        {
          "name": "My custom",
          "recipe": "Custom recipe",
          "type": "Ordinary Drink",
          "glass": "Cocktail glass",
          "alcoholic": "Alcoholic",
          "ingredientes": [
            "",
            "Vodka",
            "Gin"
          ],
          "ingredientesAmount": [
            "",
            "",
            ""
          ],
          "id": "b7400cf3-b840-4eff-a57f-c234fc158c8f"
        },
        {
          "name": "My custom",
          "recipe": "Custom recipe",
          "type": "Ordinary Drink",
          "glass": "Cocktail glass",
          "alcoholic": "Alcoholic",
          "ingredientes": [
            "",
            "Vodka",
            "Gin"
          ],
          "ingredientesAmount": [
            "",
            "",
            ""
          ],
          "id": "161bbe03-1a28-4fe8-baea-89c6bc7d8f40"
        },
        {
          "name": "My custom",
          "recipe": "Custom recipe",
          "type": "Ordinary Drink",
          "glass": "Cocktail glass",
          "alcoholic": "Alcoholic",
          "ingredientes": [
            "",
            "Vodka",
            "Gin"
          ],
          "ingredientesAmount": [
            "",
            "",
            ""
          ],
          "id": "724c72f8-c697-4c3a-8fc5-c775abbe3992"
        },
        {
          "name": "My custom",
          "recipe": "Custom recipe",
          "type": "Ordinary Drink",
          "glass": "Cocktail glass",
          "alcoholic": "Alcoholic",
          "ingredientes": [
            "",
            "Vodka",
            "Gin"
          ],
          "ingredientesAmount": [
            "",
            "",
            ""
          ],
          "id": "7828800c-adc7-45db-8581-e15391e1ece7"
        },
        {
          "name": "My custom",
          "recipe": "Custom recipe",
          "type": "Ordinary Drink",
          "glass": "Cocktail glass",
          "alcoholic": "Alcoholic",
          "ingredientes": [
            "",
            "Vodka",
            "Gin"
          ],
          "ingredientesAmount": [
            "",
            "",
            ""
          ],
          "id": "46ff05f0-ce88-41a0-8b7f-56064dff30f0"
        },
        {
          "name": "My custom",
          "recipe": "Custom recipe",
          "type": "Ordinary Drink",
          "glass": "Cocktail glass",
          "alcoholic": "Alcoholic",
          "ingredientes": [
            "",
            "Vodka",
            "Gin"
          ],
          "ingredientesAmount": [
            "",
            "",
            ""
          ],
          "id": "16987927-f7a1-4b08-a784-133b9ad10af1"
        },
        {
          "name": "My custom",
          "recipe": "Custom recipe",
          "type": "Ordinary Drink",
          "glass": "Cocktail glass",
          "alcoholic": "Alcoholic",
          "ingredientes": [
            "",
            "Vodka",
            "Gin"
          ],
          "ingredientesAmount": [
            "",
            "",
            ""
          ],
          "id": "a047263c-bea9-4e7a-9d15-ae8a56e7f533"
        },
        {
          "name": "My custom",
          "recipe": "Custom recipe",
          "type": "Ordinary Drink",
          "glass": "Cocktail glass",
          "alcoholic": "Alcoholic",
          "ingredientes": [
            "",
            "Vodka",
            "Gin"
          ],
          "ingredientesAmount": [
            "",
            "",
            ""
          ],
          "id": "cb1ac45c-b881-490b-8f8b-033a66429f22"
        },
        {
          "name": "My custom",
          "recipe": "Custom recipe",
          "type": "Ordinary Drink",
          "glass": "Cocktail glass",
          "alcoholic": "Alcoholic",
          "ingredientes": [
            "",
            "Vodka",
            "Gin"
          ],
          "ingredientesAmount": [
            "",
            "",
            ""
          ],
          "id": "37e650ac-7538-48fa-9185-0f967dfdcc13"
        },
        {
          "name": "My custom",
          "recipe": "Custom recipe",
          "type": "Ordinary Drink",
          "glass": "Cocktail glass",
          "alcoholic": "Alcoholic",
          "ingredientes": [
            "",
            "Vodka",
            "Gin"
          ],
          "ingredientesAmount": [
            "",
            "",
            ""
          ],
          "id": "de072602-ec65-4c0f-9b17-97066c81e83e"
        },
        {
          "name": "My custom",
          "recipe": "Custom recipe",
          "type": "Ordinary Drink",
          "glass": "Cocktail glass",
          "alcoholic": "Alcoholic",
          "ingredientes": [
            "",
            "Vodka",
            "Gin"
          ],
          "ingredientesAmount": [
            "",
            "",
            ""
          ],
          "id": "f3e11f48-a084-4219-a1b4-54e17e140324"
        },
        {
          "name": "My custom",
          "recipe": "Custom recipe",
          "type": "Ordinary Drink",
          "glass": "Cocktail glass",
          "alcoholic": "Alcoholic",
          "ingredientes": [
            "",
            "Vodka",
            "Gin"
          ],
          "ingredientesAmount": [
            "",
            "",
            ""
          ],
          "id": "c215cade-26e9-4616-bfc1-7710907284e8"
        },
        {
          "name": "My custom",
          "recipe": "Custom recipe",
          "type": "Ordinary Drink",
          "glass": "Cocktail glass",
          "alcoholic": "Alcoholic",
          "ingredientes": [
            "",
            "Vodka",
            "Gin"
          ],
          "ingredientesAmount": [
            "",
            "",
            ""
          ],
          "id": "59801256-feb8-481e-9207-d3ce8a447e18"
        },
        {
          "name": "My custom",
          "recipe": "Custom recipe",
          "type": "Ordinary Drink",
          "glass": "Cocktail glass",
          "alcoholic": "Alcoholic",
          "ingredientes": [
            "",
            "Vodka",
            "Gin"
          ],
          "ingredientesAmount": [
            "",
            "",
            ""
          ],
          "id": "4e1ade99-2257-4735-91a1-da7f884374ce"
        },
        {
          "name": "My custom",
          "recipe": "Custom recipe",
          "type": "Ordinary Drink",
          "glass": "Cocktail glass",
          "alcoholic": "Alcoholic",
          "ingredientes": [
            "",
            "Vodka",
            "Gin"
          ],
          "ingredientesAmount": [
            "",
            "",
            ""
          ],
          "id": "713fe693-cc91-4981-8acc-44a8a889d1bd"
        },
        {
          "name": "My custom",
          "recipe": "Custom recipe",
          "type": "Ordinary Drink",
          "glass": "Cocktail glass",
          "alcoholic": "Alcoholic",
          "ingredientes": [
            "",
            "Vodka",
            "Gin"
          ],
          "ingredientesAmount": [
            "",
            "",
            ""
          ],
          "id": "84fea303-0ef7-46d7-a38c-edbf0429a50b"
        },
        {
          "name": "My custom",
          "recipe": "Custom recipe",
          "type": "Ordinary Drink",
          "glass": "Cocktail glass",
          "alcoholic": "Alcoholic",
          "ingredientes": [
            "",
            "Vodka",
            "Gin"
          ],
          "ingredientesAmount": [
            "",
            "",
            ""
          ],
          "id": "152ea8e0-9c26-4675-a8a1-b7e5e9a957d6"
        },
        {
          "name": "My custom",
          "recipe": "Custom recipe",
          "type": "Ordinary Drink",
          "glass": "Cocktail glass",
          "alcoholic": "Alcoholic",
          "ingredientes": [
            "",
            "Vodka",
            "Gin"
          ],
          "ingredientesAmount": [
            "",
            "",
            ""
          ],
          "id": "9f2c518c-5c17-46db-bbcb-db3286891433"
        },
        {
          "name": "My custom",
          "recipe": "Custom recipe",
          "type": "Ordinary Drink",
          "glass": "Cocktail glass",
          "alcoholic": "Alcoholic",
          "ingredientes": [
            "",
            "Vodka",
            "Gin"
          ],
          "ingredientesAmount": [
            "",
            "",
            ""
          ],
          "id": "cb33e210-80f9-4c37-bdd5-77bc185a731a"
        },
        {
          "name": "My custom",
          "recipe": "Custom recipe",
          "type": "Ordinary Drink",
          "glass": "Cocktail glass",
          "alcoholic": "Alcoholic",
          "ingredientes": [
            "",
            "Vodka",
            "Gin"
          ],
          "ingredientesAmount": [
            "",
            "",
            ""
          ],
          "id": "0904719b-caa9-423f-9d36-f6b79b574907"
        },
        {
          "name": "My custom",
          "recipe": "Custom recipe",
          "type": "Ordinary Drink",
          "glass": "Cocktail glass",
          "alcoholic": "Alcoholic",
          "ingredientes": [
            "",
            "Vodka",
            "Gin"
          ],
          "ingredientesAmount": [
            "",
            "",
            ""
          ],
          "id": "a47cbc1a-f0b7-4c82-b261-b3cac30e42e4"
        },
        {
          "name": "My custom",
          "recipe": "Custom recipe",
          "type": "Ordinary Drink",
          "glass": "Cocktail glass",
          "alcoholic": "Alcoholic",
          "ingredientes": [
            "",
            "Vodka",
            "Gin"
          ],
          "ingredientesAmount": [
            "",
            "",
            ""
          ],
          "id": "628d9696-5782-4750-9355-09e40ca1bc6a"
        }
      ]
    },
    {
      "id": "moisesrj97@gmail.com",
      "fav": [
        {
          "id": "",
          "name": "",
          "thumb": "",
          "apiId": ""
        }
      ],
      "custom": [
        {
          "name": "",
          "thumb": "",
          "recipe": "",
          "type": "",
          "glass": "",
          "alcoholic": "",
          "ingredientes": [
            ""
          ],
          "ingredientesAmount": [
            ""
          ],
          "id": ""
        }
      ]
    }
  ]
}